[{
  "message": {
    "name": "RecordPostedCommentRequestBody",
    "fields": [{
      "name": "commentId",
      "type": "string",
      "index": 1
    }]
  }
}, {
  "message": {
    "name": "RecordPostedCommentResponse",
    "fields": []
  }
}, {
  "nodeService": {
    "name": "UserActivityConsumerBackendShowService",
    "remoteCalls": [{
      "name": "RecordPostedComment",
      "path": "/RecordPostedComment",
      "body": "RecordPostedCommentRequestBody",
      "response": "RecordPostedCommentResponse"
    }],
    "outputClient": "./consumer/backend/show/client",
    "outputHandler": "./consumer/backend/show/handler"
  }
}]
