[{
  "message": {
    "name": "CommentPosted",
    "fields": [{
      "name": "commentId",
      "type": "string",
      "index": 1
    }, {
      "name": "seasonId",
      "type": "string",
      "index": 2
    }, {
      "name": "seasonName",
      "type": "string",
      "index": 3
    }, {
      "name": "episodeId",
      "type": "string",
      "index": 4
    }, {
      "name": "episodeName",
      "type": "string",
      "index": 5
    }, {
      "name": "content",
      "type": "string",
      "index": 6
    }, {
      "name": "postedTime",
      "type": "string",
      "index": 7,
      "comment": "TImestamp in seconds."
    }]
  }
}]
